boring_math/pythagorean_triples/__init__.py
boring_math/pythagorean_triples/py.typed
boring_math/pythagorean_triples/pythag3.py
boring_math/pythagorean_triples/cli/__init__.py
boring_math/pythagorean_triples/cli/py.typed
boring_math/pythagorean_triples/cli/pythag3_cli.py
boring_math_pythagorean_triples-0.8.3.dist-info/entry_points.txt
boring_math_pythagorean_triples-0.8.3.dist-info/licenses/LICENSE
boring_math_pythagorean_triples-0.8.3.dist-info/WHEEL
boring_math_pythagorean_triples-0.8.3.dist-info/METADATA
boring_math_pythagorean_triples-0.8.3.dist-info/RECORD
